allowedsites.py
django_allowedsites_dynamic-0.2.1.dist-info/LICENSE
django_allowedsites_dynamic-0.2.1.dist-info/METADATA
django_allowedsites_dynamic-0.2.1.dist-info/WHEEL
django_allowedsites_dynamic-0.2.1.dist-info/top_level.txt
django_allowedsites_dynamic-0.2.1.dist-info/RECORD
