Metadata-Version: 2.1
Name: django-allowedsites-dynamic
Version: 0.2.1
Summary: dynamic ALLOWED_HOSTS
Author: Keryn Knight
Author-email: python-package@kerynknight.com
License: BSD License
Classifier: Development Status :: 4 - Beta
Classifier: Intended Audience :: Developers
Classifier: License :: OSI Approved :: BSD License
Classifier: Framework :: Django
Classifier: Natural Language :: English
Classifier: Environment :: Web Environment
Classifier: Topic :: Internet :: WWW/HTTP
Classifier: Programming Language :: Python :: 2
Classifier: Programming Language :: Python :: 2.7
Classifier: Programming Language :: Python :: 3
Classifier: Programming Language :: Python :: 3.4
Classifier: Programming Language :: Python :: 3.5
Classifier: Programming Language :: Python :: 3.6
Classifier: Programming Language :: Python :: 3.7
Classifier: Programming Language :: Python :: 3.8
Classifier: Programming Language :: Python :: 3.9
License-File: LICENSE
Requires-Dist: Django >=1.4
Requires-Dist: requests
